LICENSE
MANIFEST.in
README.md
portrait.jpg
setup.cfg
setup.py
docs/Classes.md
docs/Command-line-utility.md
docs/Communicating-with-the-server.md
docs/Developing-Wallace-(setup-guide).md
docs/Installing-Wallace-(for-users).md
docs/Learning-to-use-Wallace.md
docs/Monitoring-a-live-experiment.md
docs/Required-experimental-files.md
docs/Setting-up-AWS,-psiTurk,-MTurk,-and-Heroku.md
docs/The-Experiment-class.md
docs/Using-Postico-to-examine-a-Postgres-database.md
docs/Wallace,-the-scientist.md
docs/Wallace-with-Anaconda.md
docs/Web-API.md
docs/index.md
docs/demos/bartlett1932.md
docs/demos/chatroom.md
docs/demos/function-learning.md
docs/demos/mcmcp.md
docs/demos/rogers.md
docs/demos/assets/bartlett1932.zip
docs/demos/assets/bartlett1932.zip.zip
docs/demos/assets/chatroom.zip
docs/demos/assets/chatroom.zip.zip
docs/demos/assets/function-learning.zip
docs/demos/assets/function-learning.zip.zip
docs/demos/assets/mcmcp.zip
docs/demos/assets/mcmcp.zip.zip
docs/demos/assets/rogers.zip
docs/demos/assets/rogers.zip.zip
docs/schemas/info.csvs
docs/schemas/network.csvs
docs/schemas/node.csvs
docs/schemas/notification.csvs
docs/schemas/participant.csvs
docs/schemas/transformation.csvs
docs/schemas/transmission.csvs
docs/schemas/vector.csvs
w.egg-info/PKG-INFO
w.egg-info/SOURCES.txt
w.egg-info/dependency_links.txt
w.egg-info/entry_points.txt
w.egg-info/not-zip-safe
w.egg-info/requires.txt
w.egg-info/top_level.txt
wallace/__init__.py
wallace/__init__.pyc
wallace/command_line.py
wallace/command_line.pyc
wallace/custom.py
wallace/db.py
wallace/db.pyc
wallace/experiments.py
wallace/experiments.pyc
wallace/information.py
wallace/information.pyc
wallace/models.py
wallace/models.pyc
wallace/networks.py
wallace/networks.pyc
wallace/nodes.py
wallace/nodes.pyc
wallace/processes.py
wallace/processes.pyc
wallace/recruiters.py
wallace/recruiters.pyc
wallace/transformations.py
wallace/transformations.pyc
wallace/version.py
wallace/version.pyc
wallace/config/.wallaceconfig
wallace/frontend/static/robots.txt
wallace/frontend/static/css/wallace.css
wallace/frontend/static/scripts/reqwest.min.js
wallace/frontend/static/scripts/wallace.js
