Metadata-Version: 1.0
Name: w
Version: 0.11.1
Summary: Wallace, a platform for experimental cultural evolution
Home-page: http://github.com/berkeley-cocosci/Wallace
Author: Berkeley CoCoSci
Author-email: wallace@cocosci.berkeley.edu
License: MIT
Keywords: science,cultural evolution,experiments,psychology
Platform: UNKNOWN
